README.rst
setup.cfg
setup.py
django_sse_wrapper.egg-info/PKG-INFO
django_sse_wrapper.egg-info/SOURCES.txt
django_sse_wrapper.egg-info/dependency_links.txt
django_sse_wrapper.egg-info/not-zip-safe
django_sse_wrapper.egg-info/requires.txt
django_sse_wrapper.egg-info/top_level.txt
sse_wrapper/__init__.py
sse_wrapper/events.py
sse_wrapper/signals.py
sse_wrapper/utils.py
sse_wrapper/views.py
sse_wrapper/backends/__init__.py
sse_wrapper/backends/memory_based.py
sse_wrapper/backends/redis_based.py