Metadata-Version: 1.0
Name: django-sse-wrapper
Version: 0.0.4
Summary: A simple wrapper of the sse python implementation for django
Home-page: https://github.com/gfronza/django-sse-wrapper
Author: Germano Fronza
Author-email: germano.inf@gmail.com
License: BSD
Keywords: django,sse,xhr,polling,redis
Platform: UNKNOWN
